gpr1d/__init__.py
gpr1d/core/__init__.py
gpr1d/core/baseclasses.py
gpr1d/core/definitions.py
gpr1d/core/kernels.py
gpr1d/core/routines.py
gpr1d/core/simple.py
gpr1d/core/utils.py
gpr1d/gui/__init__.py
gpr1d/gui/gui.py
gpr1d/gui/gui.readme
gpr1d/scripts/__init__.py
gpr1d/scripts/demo.py
gpr1d/scripts/profiler.py
gpr1d-2.0.0.dist-info/LICENSE
gpr1d-2.0.0.dist-info/METADATA
gpr1d-2.0.0.dist-info/WHEEL
gpr1d-2.0.0.dist-info/entry_points.txt
gpr1d-2.0.0.dist-info/top_level.txt
gpr1d-2.0.0.dist-info/RECORD
