Metadata-Version: 2.1
Name: gpr1d
Version: 2.0.0
Summary: Classes for Gaussian Process Regression fitting of 1D data with errorbars
Author-email: Aaron Ho <aaronkho@mit.edu>
License: MIT License
Project-URL: Homepage, https://gitlab.com/aaronkho/GPR1D
Project-URL: Bug Reports, https://gitlab.com/aaronkho/GPR1D/-/issues
Project-URL: Source, https://gitlab.com/aaronkho/GPR1D
Keywords: gaussian process regression,1D data fitting,regression analysis,kriging,noisy input,heteroscedastic error
Classifier: Development Status :: 5 - Production/Stable
Classifier: Intended Audience :: Science/Research
Classifier: Topic :: Utilities
Classifier: License :: OSI Approved :: MIT License
Classifier: Programming Language :: Python :: 3.7
Classifier: Programming Language :: Python :: 3.8
Classifier: Programming Language :: Python :: 3.9
Classifier: Programming Language :: Python :: 3.10
Classifier: Programming Language :: Python :: 3.11
Classifier: Programming Language :: Python :: 3.12
Requires-Python: <3.13,>=3.7
License-File: LICENSE
Requires-Dist: pip
Requires-Dist: numpy>=1.13
Requires-Dist: scipy>=0.17
Requires-Dist: pandas
Requires-Dist: ipython
Provides-Extra: dev
Requires-Dist: coverage; extra == "dev"
Requires-Dist: pytest; extra == "dev"
Requires-Dist: pytest-cov; extra == "dev"
Provides-Extra: build
Requires-Dist: build; extra == "build"
Requires-Dist: twine; extra == "build"
Provides-Extra: demo
Requires-Dist: matplotlib; extra == "demo"
Provides-Extra: gui
Requires-Dist: pyqt5; extra == "gui"
Requires-Dist: matplotlib; extra == "gui"
Provides-Extra: profile
Requires-Dist: scikit-learn; extra == "profile"
